hqx/__init__.py
hqx/__main__.py
hqx/algor_hq2x.py
hqx/algor_hq3x.py
hqx/algor_hq4x.py
hqx/constants.py
hqx/interpolate.py
hqx/rgb_yuv.py
hqx-1.0.dist-info/LICENSE.txt
hqx-1.0.dist-info/METADATA
hqx-1.0.dist-info/WHEEL
hqx-1.0.dist-info/top_level.txt
hqx-1.0.dist-info/RECORD
