Metadata-Version: 2.1
Name: hqx
Version: 1.0
Summary: The hqx upscaling algorithm in Python
Author: WhoAteMyButter
License: LGPL-2.1-only
Project-URL: Source, https://gitlab.com/whoatemybutter/hqx_python
Project-URL: Changelog, https://gitlab.com/whoatemybutter/hqx_python/-/blob/master/CHANGELOG.md
Project-URL: Issues, https://gitlab.com/whoatemybutter/hqx_python/-/issues
Classifier: Programming Language :: Python :: 3
Classifier: Programming Language :: Python :: 3 :: Only
Classifier: Programming Language :: Python :: 3.10
Classifier: Operating System :: OS Independent
Classifier: Topic :: Utilities
Classifier: Typing :: Typed
Classifier: Development Status :: 4 - Beta
Classifier: Intended Audience :: End Users/Desktop
Classifier: Intended Audience :: Other Audience
Classifier: Intended Audience :: Developers
Classifier: License :: OSI Approved :: GNU Lesser General Public License v2 (LGPLv2)
Classifier: Topic :: Artistic Software
Classifier: Topic :: Multimedia :: Graphics
Classifier: Topic :: Multimedia
Requires-Python: >=3.10
License-File: LICENSE.txt
Requires-Dist: Pillow (>=9.3.0)
